{
    "asset": {
        "format": "jpg",
        "id": "48f18056ea8388e2765c655aebc2a53b",
        "name": "Foto(712).jpg",
        "path": "file:C:/Users/i.erturk/Desktop/BarcodeDatasets/barcode_dataset/Foto(712).jpg",
        "size": {
            "width": 1152,
            "height": 864
        },
        "state": 2,
        "type": 1
    },
    "regions": [
        {
            "id": "2jYXyAUbm",
            "type": "RECTANGLE",
            "tags": [
                "barcode"
            ],
            "boundingBox": {
                "height": 299.31428571428575,
                "width": 369.07238605898124,
                "left": 393.7801608579088,
                "top": 337.5
            },
            "points": [
                {
                    "x": 393.7801608579088,
                    "y": 337.5
                },
                {
                    "x": 762.85254691689,
                    "y": 337.5
                },
                {
                    "x": 762.85254691689,
                    "y": 636.8142857142857
                },
                {
                    "x": 393.7801608579088,
                    "y": 636.8142857142857
                }
            ]
        }
    ],
    "version": "2.2.0"
}