{
    "asset": {
        "format": "jpg",
        "id": "64121f1bc929ca820946deb4da3b4d11",
        "name": "05102009127.jpg",
        "path": "file:C:/Users/i.erturk/Desktop/BarcodeDatasets/barcode_dataset/05102009127.jpg",
        "size": {
            "width": 2048,
            "height": 1536
        },
        "state": 2,
        "type": 1
    },
    "regions": [
        {
            "id": "4BE59Mlq_",
            "type": "RECTANGLE",
            "tags": [
                "barcode"
            ],
            "boundingBox": {
                "height": 1195.8857142857144,
                "width": 1378.1447721179625,
                "left": 299.23860589812335,
                "top": 281.8285714285714
            },
            "points": [
                {
                    "x": 299.23860589812335,
                    "y": 281.8285714285714
                },
                {
                    "x": 1677.3833780160858,
                    "y": 281.8285714285714
                },
                {
                    "x": 1677.3833780160858,
                    "y": 1477.7142857142858
                },
                {
                    "x": 299.23860589812335,
                    "y": 1477.7142857142858
                }
            ]
        }
    ],
    "version": "2.2.0"
}